calculator/__init__.py
Jaidev_Chaudhary-0.0.1.dist-info/LICENSE.txt
Jaidev_Chaudhary-0.0.1.dist-info/METADATA
Jaidev_Chaudhary-0.0.1.dist-info/WHEEL
Jaidev_Chaudhary-0.0.1.dist-info/top_level.txt
Jaidev_Chaudhary-0.0.1.dist-info/RECORD
